bookforge/__init__.py
bookforge/cli.py
bookforge/config.py
bookforge/main.py
bookforge/api/__init__.py
bookforge/api/endpoints.py
bookforge/core/__init__.py
bookforge/core/book_service.py
bookforge/core/epub_generator.py
bookforge/core/github_integration.py
bookforge/core/job_manager.py
bookforge/core/markdown_processor.py
bookforge/core/models.py
bookforge/core/validator.py
bookforge/static/css/style.css
bookforge/static/js/app.js
bookforge/templates/chapter.xhtml
bookforge/templates/container.xml
bookforge/templates/content.opf
bookforge/templates/nav.xhtml
bookforge/templates/toc.ncx
bookforge/templates/themes/classic.css
bookforge/templates/themes/minimal.css
bookforge/templates/themes/modern.css
bookforge/templates/web/index.html
bookforge-0.1.0.dist-info/licenses/LICENSE
bookforge-0.1.0.dist-info/METADATA
bookforge-0.1.0.dist-info/WHEEL
bookforge-0.1.0.dist-info/entry_points.txt
bookforge-0.1.0.dist-info/top_level.txt
bookforge-0.1.0.dist-info/RECORD
