Metadata-Version: 2.4
Name: bookforge
Version: 0.1.0
Summary: Beautiful EPUB generation service - the cloud-based alternative to Vellum
Author: BookForge Team
License: MIT
Project-URL: Homepage, https://github.com/eristoddle/bookforge
Project-URL: Documentation, https://docs.bookforge.dev
Project-URL: Repository, https://github.com/eristoddle/bookforge
Project-URL: Bug Reports, https://github.com/eristoddle/bookforge/issues
Classifier: Development Status :: 3 - Alpha
Classifier: Intended Audience :: Developers
Classifier: Programming Language :: Python :: 3
Classifier: Programming Language :: Python :: 3.9
Classifier: Programming Language :: Python :: 3.10
Classifier: Programming Language :: Python :: 3.11
Classifier: Programming Language :: Python :: 3.12
Requires-Python: >=3.9
License-File: LICENSE
Requires-Dist: fastapi>=0.104.1
Requires-Dist: uvicorn[standard]>=0.24.0
Requires-Dist: python-multipart>=0.0.6
Requires-Dist: pydantic>=2.5.0
Requires-Dist: requests>=2.31.0
Requires-Dist: aiofiles>=23.2.1
Requires-Dist: python-dotenv>=1.0.0
Requires-Dist: celery>=5.3.4
Requires-Dist: redis>=5.0.1
Requires-Dist: jinja2>=3.1.2
Requires-Dist: markdown>=3.5.1
Requires-Dist: python-markdown-math>=0.8
Requires-Dist: beautifulsoup4>=4.12.2
Requires-Dist: lxml>=4.9.3
Requires-Dist: pillow>=10.1.0
Requires-Dist: zipfile36>=0.1.3
Requires-Dist: gitpython>=3.1.40
Requires-Dist: click>=8.1.7
Requires-Dist: pydantic-settings>=2.1.0
Requires-Dist: httpx>=0.25.2
Provides-Extra: dev
Requires-Dist: pytest>=7.4.0; extra == "dev"
Requires-Dist: pytest-asyncio>=0.21.0; extra == "dev"
Requires-Dist: black>=23.7.0; extra == "dev"
Requires-Dist: isort>=5.12.0; extra == "dev"
Requires-Dist: flake8>=6.0.0; extra == "dev"
Requires-Dist: mypy>=1.5.0; extra == "dev"
Dynamic: license-file
